auditd_tools/__init__.py
auditd_tools/event_parser.py
auditd_tools-0.0.3.dist-info/LICENSE
auditd_tools-0.0.3.dist-info/METADATA
auditd_tools-0.0.3.dist-info/WHEEL
auditd_tools-0.0.3.dist-info/top_level.txt
auditd_tools-0.0.3.dist-info/RECORD
