Metadata-Version: 2.1
Name: auditd-tools
Version: 0.0.3
Summary: Python tools to handle auditd events
Home-page: https://github.com/jhb/auditd_tools
Author: Joerg Baach
Author-email: mail@baach.de
Classifier: Programming Language :: Python :: 3
Classifier: License :: OSI Approved :: GNU General Public License v3 (GPLv3)
Classifier: Operating System :: OS Independent
Requires-Python: >=3.6
License-File: LICENSE
